rmsp/__init__.py
rmsp/rmsgui/__init__.py
rmsp/rmsgui/flowcontroller.py
rmsp/rmsgui/qt/__init__.py
rmsp/rmsgui/qt/action.py
rmsp/rmsgui/qt/analysis.py
rmsp/rmsgui/qt/dialog.py
rmsp/rmsgui/qt/flowview.py
rmsp/rmsgui/qt/mainapp.py
rmsp/rmsgui/qt/widget.py
rmsp/rmsgui/qt/res/__init__.py
rmsp_gui-0.0.1.data/data/rmsp/loading.gif
rmsp_gui-0.0.1.dist-info/METADATA
rmsp_gui-0.0.1.dist-info/WHEEL
rmsp_gui-0.0.1.dist-info/top_level.txt
rmsp_gui-0.0.1.dist-info/RECORD
