Metadata-Version: 2.1
Name: rmsp-gui
Version: 0.0.1
Summary: Resource management system GUI for python
Home-page: https://github.com/aldenleung/rmsp-gui/
Author: Alden Leung
Author-email: alden.leung@gmail.com
License: UNKNOWN
Platform: UNKNOWN
Classifier: Programming Language :: Python :: 3.7
Classifier: Programming Language :: Python :: 3.8
Classifier: Programming Language :: Python :: 3.9
Classifier: License :: OSI Approved :: GNU General Public License v3 (GPLv3)
Requires-Dist: PyQt5
Requires-Dist: networkx
Requires-Dist: matplotlib
Requires-Dist: matplotlib-venn
Requires-Dist: genomictools
Requires-Dist: biodata
Requires-Dist: rmsp
Requires-Dist: pyBigWig
